{
  "project_info": {
    "project_number": "700095714481",
    "project_id": "jooders-d8330",
    "storage_bucket": "jooders-d8330.appspot.com"
  },
  "client": [
    {
      "client_info": {
        "mobilesdk_app_id": "1:700095714481:android:6255bfc78f126686513e90",
        "android_client_info": {
          "package_name": "com.airjood"
        }
      },
      "oauth_client": [],
      "api_key": [
        {
          "current_key": "AIzaSyBGp1tPZnzX_1vmPq75tjggzYNWnHUGe0A"
        }
      ],
      "services": {
        "appinvite_service": {
          "other_platform_oauth_client": []
        }
      }
    }
  ],
  "configuration_version": "1"
}